ip2loc_server/__init__.py
ip2loc_server/config.py
ip2loc_server/data.py
ip2loc_server/ip2loc.py
ip2loc_server/server.py
ip2loc_server/util.py
ip2loc_server/data/IP2LOCATION-LITE-DB5.CSV.ZIP
ip2loc_server/data/data_version
tests/__init__.py
ip2loc_server-0.0.1.dist-info/LICENSE
ip2loc_server-0.0.1.dist-info/METADATA
ip2loc_server-0.0.1.dist-info/WHEEL
ip2loc_server-0.0.1.dist-info/entry_points.txt
ip2loc_server-0.0.1.dist-info/top_level.txt
ip2loc_server-0.0.1.dist-info/RECORD
