Metadata-Version: 2.1
Name: ip2loc-server
Version: 0.0.1
Summary: A tiny web server for ipv4 to geo location conversion
Home-page: https://github.com/ZhenningLang/ip2loc_server
Author: ZhenningLang
Author-email: zhenninglang@163.com
License: UNKNOWN
Platform: UNKNOWN
Classifier: Programming Language :: Python :: 3
Classifier: License :: OSI Approved :: MIT License
Classifier: Operating System :: OS Independent
Requires-Python: >=3.5
